Workbook

Sheet Assumption sheet
B1: Infosys
B2: Assumption | C2: Value | D2: Note
B3: Revenue Growth (Year 1–2) | C3: 0.12 | D3: Higher initial growth
B4: Revenue Growth (Year 3–5) | C4: 0.08 | D4: Slowing growth
B5: EBIT Margin | C5: 0.23 | D5: Based on industry
B6: Tax Rate | C6: 0.25 | D6: India corporate tax
B7: CapEx (% Revenue) | C7: 0.04 | D7: IT companies low capex
B8: Working Capital (% Revenue) | C8: 0.01 | D8: Low for IT
B9: Discount Rate (WACC) | C9: 0.1 | D9: Standard
B10: Terminal Growth | C10: 0.03 | D10: Long-term GDP-like

Sheet Historical data
B3: Year | C3: Revenue | D3: Ebit | E3: Net Profit
B4: 2021 | C4: 1,00,472 | D4: 26628 | E4: 19351
B5: 2022 | C5: 1,21,641 | D5: 30084 | E5: 22146
B6: 2023 | C6: 1,46,767 | D6: 36153 | E6: 24095
B7: 2024 | C7: 1,53,670 | D7: 37510 | E7: 25000

Sheet Forcast 
B3: Year | C3: Revenue | D3: Ebit | E3: Tax | F3: NOPAT | G3: Capex | H3: WC | I3: FCF
B4: 2025 | C4: =153670*(1+12/100) -> 172110.4 | D4: =C4*0.23 -> 39585.392 | E4: =D4*0.25 -> 9896.348 | F4: =D4-E4 -> 29689.044 | G4: =C4*0.04 -> 6884.416 | H4: =C4*0.01 -> 1721.104 | I4: =F4-G4-H4 -> 21083.524
B5: 2026 | C5: =172110.4*(1+12/100) -> 192763.65 | D5: =C5*0.23 -> 44335.639 | E5: =D5*0.25 -> 11083.91 | F5: =D5-E5 -> 33251.729 | G5: =C5*0.04 -> 7710.5459 | H5: =C5*0.01 -> 1927.6365 | I5: =F5-G5-H5 -> 23613.547
B6: 2027 | C6: =192763.6*(1+8/100) -> 208184.69 | D6: =C6*0.23 -> 47882.478 | E6: =D6*0.25 -> 11970.62 | F6: =D6-E6 -> 35911.859 | G6: =C6*0.04 -> 8327.3875 | H6: =C6*0.01 -> 2081.8469 | I6: =F6-G6-H6 -> 25502.624
B7: 2028 | C7: =208184.7*(1+8/100) -> 224839.48 | D7: =C7*0.23 -> 51713.079 | E7: =D7*0.25 -> 12928.27 | F7: =D7-E7 -> 38784.81 | G7: =C7*0.04 -> 8993.579 | H7: =C7*0.01 -> 2248.3948 | I7: =F7-G7-H7 -> 27542.836
B8: 2029 | C8: =224839.5*(1+8/100) -> 242826.66 | D8: =C8*0.23 -> 55850.132 | E8: =D8*0.25 -> 13962.533 | F8: =D8-E8 -> 41887.599 | G8: =C8*0.04 -> 9713.0664 | H8: =C8*0.01 -> 2428.2666 | I8: =F8-G8-H8 -> 29746.266

Sheet DCF model
B3: Year | C3: FCF | D3: Discount Factor | E3: Present Value
B4: 2025 | C4: ='Forcast '!I4 -> 21083.524 | D4: =1/(1+0.1)^1 -> 0.90909091 | E4: =C4*D4 -> 19166.84
B5: 2026 | C5: ='Forcast '!I5 -> 23613.547 | D5: =1/(1+0.1)^2 -> 0.82644628 | E5: =C5*D5 -> 19515.328
B6: 2027 | C6: ='Forcast '!I6 -> 25502.624 | D6: =1/(1+0.1)^3 -> 0.7513148 | E6: =C6*D6 -> 19160.499
B7: 2028 | C7: ='Forcast '!I7 -> 27542.836 | D7: =1/(1+0.1)^4 -> 0.68301346 | E7: =C7*D7 -> 18812.127
B8: 2029 | C8: ='Forcast '!I8 -> 29746.266 | D8: =1/(1+0.1)^5 -> 0.62092132 | E8: =C8*D8 -> 18470.091
G11: Result
A12: sum of present value | D12: =SUM(E4:E8) -> 95124.885 | G12: Enterprise value | I12: =D12+D14 -> 358983.32
A13: Terminal value | D13: =C8/(0.1-0.03) -> 424946.66 | G13: Discount Rate | I13: 0.1
A14: DISCOUNT TERMINAL VALUE | D14: =D13/(1+10%)^5 -> 263858.44 | G14: Terminal Growth | I14: 0.03
A15: Enterprise value | D15: =D12+D14 -> 358983.32
